slicr/__init__.py
slicr/__main__.py
slicr-0.1.2.dist-info/licenses/LICENSE
slicr-0.1.2.dist-info/METADATA
slicr-0.1.2.dist-info/WHEEL
slicr-0.1.2.dist-info/entry_points.txt
slicr-0.1.2.dist-info/top_level.txt
slicr-0.1.2.dist-info/RECORD
