Metadata-Version: 2.4
Name: slicr
Version: 0.1.2
Summary: A tiny CLI that prints hello world.
Author: Oliver Chester
License: MIT License
Project-URL: Homepage, https://github.com/oliver-gc/slicr
Project-URL: Repository, https://github.com/oliver-gc/slicr
Classifier: Programming Language :: Python :: 3
Classifier: License :: OSI Approved :: MIT License
Classifier: Operating System :: OS Independent
Requires-Python: >=3.8
License-File: LICENSE
Dynamic: license-file
